aginstaller/__init__.py
aginstaller/androidInstaller.py
aginstaller-0.0.2.dist-info/METADATA
aginstaller-0.0.2.dist-info/WHEEL
aginstaller-0.0.2.dist-info/licenses/LICENSE
aginstaller-0.0.2.dist-info/RECORD
