Metadata-Version: 2.3
Name: aginstaller
Version: 0.0.2
Summary: install apk for test, beta.
Author-email: Bruce <bruceamadeuslee@gmail.com>
License-File: LICENSE
Classifier: License :: OSI Approved :: MIT License
Classifier: Operating System :: OS Independent
Classifier: Programming Language :: Python :: 3
Requires-Python: >=3.8
